{
  "schemaVersion": "1.0",
  "id": "g10-070",
  "kanji": "刹",
  "grade": 10,
  "strokeCount": 8,
  "viewBox": [
    0,
    0,
    100,
    100
  ],
  "strokes": [
    {
      "index": 1,
      "path": "M 44.16 12.55 c 0.11 0.75 0.55 2.11 -0.23 3.16 C 36.92 25.05 28.76 32.1 15.6 38.3",
      "start": [
        44.16,
        12.55
      ],
      "end": [
        15.6,
        38.3
      ]
    },
    {
      "index": 2,
      "path": "M 19.91 17.86 c 7.37 1.22 21.8 9.33 27.83 18.35",
      "start": [
        19.91,
        17.86
      ],
      "end": [
        27.83,
        18.35
      ]
    },
    {
      "index": 3,
      "path": "M 11.5 52.94 c 0.5 0.22 3.46 0.38 4.78 0.28 c 5.7 -0.38 21.32 -2.94 30.49 -4.05 c 1.32 -0.16 3.11 -0.22 3.94 0",
      "start": [
        11.5,
        52.94
      ],
      "end": [
        3.94,
        0
      ]
    },
    {
      "index": 4,
      "path": "M 33.28 37.16 c 1 0.43 1.48 2.06 1.48 4.51 c 0 0.88 -0.13 43.35 -0.33 48.7",
      "start": [
        33.28,
        37.16
      ],
      "end": [
        -0.33,
        48.7
      ]
    },
    {
      "index": 5,
      "path": "M 34.25 53.01 C 29.13 63.53 19.72 73.62 11.03 79.44",
      "start": [
        34.25,
        53.01
      ],
      "end": [
        11.03,
        79.44
      ]
    },
    {
      "index": 6,
      "path": "M 37.93 59.31 c 3.11 1.72 8.4 6.28 10.86 10.64",
      "start": [
        37.93,
        59.31
      ],
      "end": [
        10.86,
        10.64
      ]
    },
    {
      "index": 7,
      "path": "M 62.17 23.24 c 0.9 0.84 1.53 1.83 1.61 4.61 C 64.15 41.2 63.76 57.83 63.76 62.39",
      "start": [
        62.17,
        23.24
      ],
      "end": [
        63.76,
        62.39
      ]
    },
    {
      "index": 8,
      "path": "M 81.44 12.23 c 0.9 0.84 1.53 1.83 1.61 4.61 c 0.37 13.35 -0.24 60.24 -0.24 64.79 c 0 12.06 -6.61 1.38 -7.99 0.23",
      "start": [
        81.44,
        12.23
      ],
      "end": [
        -7.99,
        0.23
      ]
    }
  ]
}