{
  "schemaVersion": "1.0",
  "id": "g8-021",
  "kanji": "慨",
  "grade": 8,
  "strokeCount": 13,
  "viewBox": [
    0,
    0,
    100,
    100
  ],
  "strokes": [
    {
      "index": 1,
      "path": "M 13.73 33.03 c 0 5.98 -3.41 14.81 -4.3 16.51",
      "start": [
        13.73,
        33.03
      ],
      "end": [
        -4.3,
        16.51
      ]
    },
    {
      "index": 2,
      "path": "M 23.96 29.82 c 2.33 1.45 6.01 5.97 6.59 8.23",
      "start": [
        23.96,
        29.82
      ],
      "end": [
        6.59,
        8.23
      ]
    },
    {
      "index": 3,
      "path": "M 20.29 14.45 c 0.81 0.92 1.11 2.29 1.11 4.13 c 0 5.8 0.02 47.61 0.03 63.87 c 0 2.83 0 4.89 0 5.85",
      "start": [
        20.29,
        14.45
      ],
      "end": [
        0,
        5.85
      ]
    },
    {
      "index": 4,
      "path": "M 35.52 20.72 c 1.4 0.61 2.83 0.52 4.44 0.21 c 3.32 -0.64 7.53 -1.44 9.7 -1.83 c 2.36 -0.43 3.39 0.08 3.29 2.7 c -0.2 5.34 -1.26 14.75 -1.81 20.43 c -0.17 1.71 -0.3 3.06 -0.39 3.83",
      "start": [
        35.52,
        20.72
      ],
      "end": [
        -0.39,
        3.83
      ]
    },
    {
      "index": 5,
      "path": "M 38.14 33.46 c 3.89 -0.67 8.33 -1.71 12.88 -2.24",
      "start": [
        38.14,
        33.46
      ],
      "end": [
        12.88,
        -2.24
      ]
    },
    {
      "index": 6,
      "path": "M 38.3 45.89 c 2.89 -0.37 7.58 -1.32 11.68 -1.85",
      "start": [
        38.3,
        45.89
      ],
      "end": [
        11.68,
        -1.85
      ]
    },
    {
      "index": 7,
      "path": "M 35.98 21.17 c 0.66 0.66 1.07 1.41 1.07 2.55 c 0 3.25 -0.01 38.43 -0.01 47.72 c 0 5.05 0.11 5.16 3.9 1.83 c 2.97 -2.61 5.62 -5.05 11.09 -9.76",
      "start": [
        35.98,
        21.17
      ],
      "end": [
        11.09,
        -9.76
      ]
    },
    {
      "index": 8,
      "path": "M 49.43 57.11 c 2.01 1.91 5.01 7.06 5.87 11.44",
      "start": [
        49.43,
        57.11
      ],
      "end": [
        5.87,
        11.44
      ]
    },
    {
      "index": 9,
      "path": "M 60.82 21.92 c 1.8 0.21 3.65 0.17 5.15 -0.09 c 3.81 -0.65 8.83 -1.61 13.06 -2.05 c 1.44 -0.15 2.74 -0.21 4.15 0.17",
      "start": [
        60.82,
        21.92
      ],
      "end": [
        4.15,
        0.17
      ]
    },
    {
      "index": 10,
      "path": "M 63.34 23.32 c 0.42 0.76 0.54 1.68 0.49 2.85 c -0.19 3.9 -0.86 10.29 -1.42 17.38",
      "start": [
        63.34,
        23.32
      ],
      "end": [
        -1.42,
        17.38
      ]
    },
    {
      "index": 11,
      "path": "M 55.75 44.75 c 1.94 0.28 3.55 0.2 5.5 -0.06 C 66.88 43.94 74.75 42.57 82.57 41.83 c 1.67 -0.16 3.16 -0.21 4.82 0.07",
      "start": [
        55.75,
        44.75
      ],
      "end": [
        4.82,
        0.07
      ]
    },
    {
      "index": 12,
      "path": "M 75.58 23.06 c 0.34 0.81 0.54 1.94 0.2 3.89 C 72.94 43.12 67.43 66.28 52.75 80.28",
      "start": [
        75.58,
        23.06
      ],
      "end": [
        52.75,
        80.28
      ]
    },
    {
      "index": 13,
      "path": "M 72.39 51.85 c 0.95 0.95 1.19 2.28 1.19 3.78 c 0 7.09 -0.07 12.6 -0.07 20.5 s 1.48 8.94 8.3 8.94 s 7.63 -1.05 7.63 -7.28",
      "start": [
        72.39,
        51.85
      ],
      "end": [
        7.63,
        -7.28
      ]
    }
  ]
}