{
  "schemaVersion": "1.0",
  "id": "g2-139",
  "kanji": "è",
  "grade": 2,
  "strokeCount": 14,
  "viewBox": [
    0,
    0,
    100,
    100
  ],
  "strokes": [
    {
      "index": 1,
      "path": "M 14.81 16.49 c 0.86 0.86 1.39 1.98 1.39 2.98 c 0 0.71 -0.03 44.45 -0.17 60.82 c -0.03 2.9 -0.05 4.93 -0.06 5.7",
      "start": [
        14.81,
        16.49
      ],
      "end": [
        -0.06,
        5.7
      ]
    },
    {
      "index": 2,
      "path": "M 17.44 17.98 c 6.29 -1.12 16.96 -2.84 19.34 -3.11 c 1.74 -0.19 2.78 0.72 2.75 2.26 c -0.04 1.69 -0.54 9.6 -1.32 18.37 c -0.08 0.95 -0.14 1.83 -0.14 2.47",
      "start": [
        17.44,
        17.98
      ],
      "end": [
        -0.14,
        2.47
      ]
    },
    {
      "index": 3,
      "path": "M 17.26 27.92 c 6.37 -0.96 14.51 -2.34 20.56 -2.66",
      "start": [
        17.26,
        27.92
      ],
      "end": [
        20.56,
        -2.66
      ]
    },
    {
      "index": 4,
      "path": "M 16.39 39.06 C 24.08 37.84 30.28 36.7 37.08 36.15",
      "start": [
        16.39,
        39.06
      ],
      "end": [
        37.08,
        36.15
      ]
    },
    {
      "index": 5,
      "path": "M 60.74 13.05 c 0.61 0.61 1.07 1.63 1.07 2.69 c 0 0.51 0.11 12.1 0.16 17.52 c 0.02 1.57 0.03 2.6 0.03 2.67",
      "start": [
        60.74,
        13.05
      ],
      "end": [
        0.03,
        2.67
      ]
    },
    {
      "index": 6,
      "path": "M 62.85 14.77 c 6.32 -1.01 17.69 -2.99 19.42 -3.08 c 1.8 -0.09 3.28 1.27 3.28 2.73 c 0 17.23 -0.24 55.3 -0.24 67.79 c 0 10.21 -5.84 1.95 -7.53 0.23",
      "start": [
        62.85,
        14.77
      ],
      "end": [
        -7.53,
        0.23
      ]
    },
    {
      "index": 7,
      "path": "M 62.93 23.8 c 4.73 -0.63 16.66 -2.24 21.1 -2.49",
      "start": [
        62.93,
        23.8
      ],
      "end": [
        21.1,
        -2.49
      ]
    },
    {
      "index": 8,
      "path": "M 63.42 33.72 c 5.84 -0.69 13.87 -1.83 20.32 -2.32",
      "start": [
        63.42,
        33.72
      ],
      "end": [
        20.32,
        -2.32
      ]
    },
    {
      "index": 9,
      "path": "M 30.73 47.01 c 1.57 0.28 3.69 0.23 5.24 0.06 c 8.81 -0.96 18.54 -2.8 28.13 -3.72 c 2.6 -0.25 4.19 -0.09 5.5 0.05",
      "start": [
        30.73,
        47.01
      ],
      "end": [
        5.5,
        0.05
      ]
    },
    {
      "index": 10,
      "path": "M 39.18 48.62 c 0.82 0.82 1.19 2.07 1.19 3.22 S 40.37 72.76 40.37 76.92",
      "start": [
        39.18,
        48.62
      ],
      "end": [
        40.37,
        76.92
      ]
    },
    {
      "index": 11,
      "path": "M 41.4 56.36 c 4.12 -0.39 12.61 -1.88 18.15 -2.17",
      "start": [
        41.4,
        56.36
      ],
      "end": [
        18.15,
        -2.17
      ]
    },
    {
      "index": 12,
      "path": "M 41.11 65.75 c 5.25 -0.61 11.29 -1.76 18.46 -2.71",
      "start": [
        41.11,
        65.75
      ],
      "end": [
        18.46,
        -2.71
      ]
    },
    {
      "index": 13,
      "path": "M 29.83 78.11 c 0.91 0.79 2.02 1.13 2.98 0.84 c 4.47 -1.31 25.87 -7.18 31.89 -8.61",
      "start": [
        29.83,
        78.11
      ],
      "end": [
        31.89,
        -8.61
      ]
    },
    {
      "index": 14,
      "path": "M 59.49 45.56 c 0.57 0.58 0.96 1.57 0.96 2.74 c 0 0.61 0.11 25.28 0.14 35.87 c 0.01 1.72 0.01 3.08 0.01 3.9",
      "start": [
        59.49,
        45.56
      ],
      "end": [
        0.01,
        3.9
      ]
    }
  ]
}