{
  "schemaVersion": "1.0",
  "id": "g7-310",
  "kanji": "露",
  "grade": 7,
  "strokeCount": 21,
  "viewBox": [
    0,
    0,
    100,
    100
  ],
  "strokes": [
    {
      "index": 1,
      "path": "M 31.82 14.35 c 2.01 0.24 4.15 0.27 6.16 0.05 c 5.6 -0.63 14.97 -1.74 22.7 -2.27 c 2.12 -0.15 4.09 -0.15 6.2 0.17",
      "start": [
        31.82,
        14.35
      ],
      "end": [
        6.2,
        0.17
      ]
    },
    {
      "index": 2,
      "path": "M 18.36 24.42 c -0.2 4.79 -2 10.09 -3.33 14.94",
      "start": [
        18.36,
        24.42
      ],
      "end": [
        -3.33,
        14.94
      ]
    },
    {
      "index": 3,
      "path": "M 19.36 26.45 c 19.29 -1.39 47.16 -4.37 60.89 -4.37 c 7.11 0 3.43 4.03 -0.25 7.58",
      "start": [
        19.36,
        26.45
      ],
      "end": [
        -0.25,
        7.58
      ]
    },
    {
      "index": 4,
      "path": "M 47.9 15.73 c 0.92 0.92 1.12 2.04 1.12 3.38 c 0 0.32 0.11 11.01 0.06 17.81 c -0.03 2.56 -0.04 4.44 -0.04 4.77",
      "start": [
        47.9,
        15.73
      ],
      "end": [
        -0.04,
        4.77
      ]
    },
    {
      "index": 5,
      "path": "M 29.34 29.77 c 2.46 0.65 5.8 2.6 7.14 3.67",
      "start": [
        29.34,
        29.77
      ],
      "end": [
        7.14,
        3.67
      ]
    },
    {
      "index": 6,
      "path": "M 27.58 37.08 c 2.22 0.64 5.65 3.02 6.86 4.1",
      "start": [
        27.58,
        37.08
      ],
      "end": [
        6.86,
        4.1
      ]
    },
    {
      "index": 7,
      "path": "M 59.42 27.38 c 2.99 0.94 6.38 2.83 7.57 3.61",
      "start": [
        59.42,
        27.38
      ],
      "end": [
        7.57,
        3.61
      ]
    },
    {
      "index": 8,
      "path": "M 59.22 34.93 c 2.33 0.63 5.92 2.94 7.19 4",
      "start": [
        59.22,
        34.93
      ],
      "end": [
        7.19,
        4
      ]
    },
    {
      "index": 9,
      "path": "M 20.55 47.73 c 0.68 0.41 1.17 0.85 1.43 2.05 c 0.61 2.74 1.1 4.5 1.66 7.29 c 0.25 1.25 0.48 2.45 0.67 3.47",
      "start": [
        20.55,
        47.73
      ],
      "end": [
        0.67,
        3.47
      ]
    },
    {
      "index": 10,
      "path": "M 22.53 48.43 c 7.05 -1.04 13 -1.88 16.93 -2.24 c 2.15 -0.19 3.31 0.83 2.68 2.91 c -0.68 2.24 -1.39 4.7 -2.26 7.56",
      "start": [
        22.53,
        48.43
      ],
      "end": [
        -2.26,
        7.56
      ]
    },
    {
      "index": 11,
      "path": "M 25.04 58.85 c 3.4 -0.29 7.58 -0.77 12.09 -1.24 c 1.21 -0.13 2.45 -0.25 3.7 -0.38",
      "start": [
        25.04,
        58.85
      ],
      "end": [
        3.7,
        -0.38
      ]
    },
    {
      "index": 12,
      "path": "M 31.07 60.92 c 0.96 0.96 1.11 2.16 1.11 3.62 c 0 3.12 0.03 9.89 0.03 15.39",
      "start": [
        31.07,
        60.92
      ],
      "end": [
        0.03,
        15.39
      ]
    },
    {
      "index": 13,
      "path": "M 32.92 67.62 c 2.86 -0.65 4.48 -0.82 7.43 -1.39 c 0.93 -0.18 1.77 -0.16 2.76 0",
      "start": [
        32.92,
        67.62
      ],
      "end": [
        2.76,
        0
      ]
    },
    {
      "index": 14,
      "path": "M 20.29 70.02 c 0.72 0.72 0.88 1.77 0.88 2.94 c 0 0.65 0.03 6.63 0.03 10.7",
      "start": [
        20.29,
        70.02
      ],
      "end": [
        0.03,
        10.7
      ]
    },
    {
      "index": 15,
      "path": "M 15.14 85.03 c 0.92 0.98 2.04 1.01 3.39 0.55 c 7.96 -2.67 14.39 -4.84 23.44 -8.17",
      "start": [
        15.14,
        85.03
      ],
      "end": [
        23.44,
        -8.17
      ]
    },
    {
      "index": 16,
      "path": "M 57.72 41.14 c 0.06 0.86 0.01 1.54 -0.31 2.36 c -1.59 3.94 -5.42 9.49 -10.83 15.5",
      "start": [
        57.72,
        41.14
      ],
      "end": [
        -10.83,
        15.5
      ]
    },
    {
      "index": 17,
      "path": "M 58.12 45.41 c 0.25 0.02 1.31 0 2.02 -0.06 c 2.21 -0.19 6.86 -0.83 10.16 -1.53 c 2.17 -0.47 3.44 0.8 2.23 2.9 c -4.14 7.19 -15.5 22.4 -29.01 26.5",
      "start": [
        58.12,
        45.41
      ],
      "end": [
        -29.01,
        26.5
      ]
    },
    {
      "index": 18,
      "path": "M 54.01 51.53 c 2.69 0.75 17.06 10.78 24.88 15.41 c 2.76 1.63 4.37 2.32 7.17 3.27",
      "start": [
        54.01,
        51.53
      ],
      "end": [
        7.17,
        3.27
      ]
    },
    {
      "index": 19,
      "path": "M 51.03 73.96 c 0.67 0.66 1.03 1.47 1.07 2.43 c 0.59 2.61 1.19 6.8 1.69 10.52 c 0.18 1.36 0.35 2.65 0.49 3.79",
      "start": [
        51.03,
        73.96
      ],
      "end": [
        0.49,
        3.79
      ]
    },
    {
      "index": 20,
      "path": "M 52.74 74.76 c 6.69 -0.71 16.26 -1.91 20.65 -2.41 c 2.42 -0.28 3.41 0.18 2.87 2.68 c -0.68 3.11 -1.47 7.08 -2.44 11.02",
      "start": [
        52.74,
        74.76
      ],
      "end": [
        -2.44,
        11.02
      ]
    },
    {
      "index": 21,
      "path": "M 55.1 88.2 c 3.17 -0.32 10.71 -0.83 16.48 -1.35 c 1.57 -0.14 2.85 -0.39 4.19 -0.18",
      "start": [
        55.1,
        88.2
      ],
      "end": [
        4.19,
        -0.18
      ]
    }
  ]
}