{
  "schemaVersion": "1.0",
  "id": "g9-161",
  "kanji": "迅",
  "grade": 9,
  "strokeCount": 6,
  "viewBox": [
    0,
    0,
    100,
    100
  ],
  "strokes": [
    {
      "index": 1,
      "path": "M 40.37 20.25 c 2.06 0.71 3.96 0.61 6.06 0.21 c 10.58 -2 14.36 -3.15 19.88 -4.12 c 3.86 -0.68 4.87 0.04 4.04 3.96 c -3.81 17.83 -3.16 35.83 10.99 47.66 c 6.15 5.14 4.5 1.82 4.69 -3.27",
      "start": [
        40.37,
        20.25
      ],
      "end": [
        4.69,
        -3.27
      ]
    },
    {
      "index": 2,
      "path": "M 36.93 45.23 c 2.06 0.52 4.07 0.32 5.74 0.11 C 46.93 44.81 52.29 43.67 58.17 42.83 c 1.23 -0.17 2.16 -0.39 3.3 -0.16",
      "start": [
        36.93,
        45.23
      ],
      "end": [
        3.3,
        -0.16
      ]
    },
    {
      "index": 3,
      "path": "M 49.14 29.82 c 0.83 0.83 1.03 1.83 1.03 3.21 c 0 5.99 0.04 24.01 0.05 33.49 c 0.01 3.12 0.01 5.31 0.01 5.85",
      "start": [
        49.14,
        29.82
      ],
      "end": [
        0.01,
        5.85
      ]
    },
    {
      "index": 4,
      "path": "M 19.23 17.66 c 3.33 1.6 8.61 6.58 9.44 9.06",
      "start": [
        19.23,
        17.66
      ],
      "end": [
        9.44,
        9.06
      ]
    },
    {
      "index": 5,
      "path": "M 11.93 46.56 c 2.06 0.92 3.92 0.3 4.82 0 c 4.13 -1.38 7.85 -2.84 9.17 -3.44 c 2.29 -1.03 3.67 0.35 2.52 2.52 c -6.73 12.8 -6.65 7.8 0.23 17.66 c 0.88 1.27 0.69 2.52 -0.69 3.67 s -5.05 4.59 -8.49 7.11",
      "start": [
        11.93,
        46.56
      ],
      "end": [
        -8.49,
        7.11
      ]
    },
    {
      "index": 6,
      "path": "M 13.99 76.38 c 2.75 -0.46 10.27 -0.86 14.45 -0.23 c 6.07 0.92 25.52 6.39 29.59 7.57 c 11.01 3.21 14.45 3.9 23.85 4.59",
      "start": [
        13.99,
        76.38
      ],
      "end": [
        23.85,
        4.59
      ]
    }
  ]
}