{
  "schemaVersion": "1.0",
  "id": "g6-182",
  "kanji": "翌",
  "grade": 6,
  "strokeCount": 11,
  "viewBox": [
    0,
    0,
    100,
    100
  ],
  "strokes": [
    {
      "index": 1,
      "path": "M 16.72 18.35 c 1.62 0.92 2.95 0.92 5.28 0.54 c 4.73 -0.77 12.81 -2.21 14.26 -2.39 c 2.61 -0.33 3.83 0.36 3.83 2.57 c 0 3.99 0.03 17.03 0.03 26.9 c 0 7.51 -5.16 0.88 -5.75 0.27",
      "start": [
        16.72,
        18.35
      ],
      "end": [
        -5.75,
        0.27
      ]
    },
    {
      "index": 2,
      "path": "M 20.07 25.46 c 2.77 1.01 7.15 4.14 7.84 5.71",
      "start": [
        20.07,
        25.46
      ],
      "end": [
        7.84,
        5.71
      ]
    },
    {
      "index": 3,
      "path": "M 15.77 44.78 c 1.15 0.57 2.21 0.66 3.43 -0.06 c 0.96 -0.58 8.68 -5.7 12.75 -8.47",
      "start": [
        15.77,
        44.78
      ],
      "end": [
        12.75,
        -8.47
      ]
    },
    {
      "index": 4,
      "path": "M 52.37 15.6 c 1.42 0.57 2.95 0.69 5.28 0.31 c 4.74 -0.77 14.86 -2.98 16.28 -3.3 c 2.45 -0.56 3.83 1.05 3.83 2.57 c 0 2.99 -0.01 20.41 -0.01 29.62 c 0 6.62 -5.6 0.82 -6.25 0.25",
      "start": [
        52.37,
        15.6
      ],
      "end": [
        -6.25,
        0.25
      ]
    },
    {
      "index": 5,
      "path": "M 56.01 23.01 c 2.58 0.99 6.65 4.08 7.29 5.62",
      "start": [
        56.01,
        23.01
      ],
      "end": [
        7.29,
        5.62
      ]
    },
    {
      "index": 6,
      "path": "M 52.32 41.34 c 1.28 0.76 2.41 0.98 3.74 0.19 c 0.92 -0.55 9.08 -5.57 12.19 -8.04",
      "start": [
        52.32,
        41.34
      ],
      "end": [
        12.19,
        -8.04
      ]
    },
    {
      "index": 7,
      "path": "M 47.94 47.48 c 0.92 0.69 1.38 2.06 1.38 3.67 s 0 3.21 0 7.57",
      "start": [
        47.94,
        47.48
      ],
      "end": [
        0,
        7.57
      ]
    },
    {
      "index": 8,
      "path": "M 26.15 61.43 c 2.02 0.57 4.72 0.39 6.78 0.17 c 7.94 -0.84 23.8 -2.99 32.68 -3.73 c 2.45 -0.2 4.89 -0.17 7.33 0.24",
      "start": [
        26.15,
        61.43
      ],
      "end": [
        7.33,
        0.24
      ]
    },
    {
      "index": 9,
      "path": "M 35.32 68.35 c 2.98 3.33 4.94 6.88 5.96 10.78",
      "start": [
        35.32,
        68.35
      ],
      "end": [
        5.96,
        10.78
      ]
    },
    {
      "index": 10,
      "path": "M 63.07 61.47 c 0.57 1.27 0.46 2.52 0 3.9 c -2.61 7.84 -4.36 11.93 -6.65 17.89",
      "start": [
        63.07,
        61.47
      ],
      "end": [
        -6.65,
        17.89
      ]
    },
    {
      "index": 11,
      "path": "M 15.37 86.51 c 2.65 0.71 6.12 0.61 8.83 0.31 c 15.62 -1.68 35.63 -3.47 51.83 -3.95 c 3.33 -0.1 6.68 0.16 9.98 0.69",
      "start": [
        15.37,
        86.51
      ],
      "end": [
        9.98,
        0.69
      ]
    }
  ]
}