{
  "schemaVersion": "1.0",
  "id": "g6-100",
  "kanji": "è–",
  "grade": 6,
  "strokeCount": 13,
  "viewBox": [
    0,
    0,
    100,
    100
  ],
  "strokes": [
    {
      "index": 1,
      "path": "M 15.31 16.97 c 1.61 0.51 4.09 0.46 5.8 0.23 c 7.68 -1.03 16.73 -2.77 23.94 -3.47 c 2.02 -0.19 4.13 -0.18 6.09 0.18",
      "start": [
        15.31,
        16.97
      ],
      "end": [
        6.09,
        0.18
      ]
    },
    {
      "index": 2,
      "path": "M 23.79 20.25 c 0.81 0.81 0.94 2.14 0.94 3.41 c 0 3.63 -0.07 19.61 -0.07 25.54",
      "start": [
        23.79,
        20.25
      ],
      "end": [
        -0.07,
        25.54
      ]
    },
    {
      "index": 3,
      "path": "M 25.73 27.28 c 6.94 -1.36 11.53 -1.94 17.73 -2.83",
      "start": [
        25.73,
        27.28
      ],
      "end": [
        17.73,
        -2.83
      ]
    },
    {
      "index": 4,
      "path": "M 25.45 38.26 C 31.19 37.16 37.27 35.78 44.41 34.77",
      "start": [
        25.45,
        38.26
      ],
      "end": [
        44.41,
        34.77
      ]
    },
    {
      "index": 5,
      "path": "M 12.84 52.65 c 0.92 0.79 2.21 0.89 3.17 0.58 c 5.9 -1.96 16.22 -5.17 27 -8.87",
      "start": [
        12.84,
        52.65
      ],
      "end": [
        27,
        -8.87
      ]
    },
    {
      "index": 6,
      "path": "M 43.81 16.97 c 0.57 0.57 1.01 1.57 1.01 2.84 c 0 1.12 -0.12 17.14 -0.09 28.12 c 0 1.49 0.01 2.88 0.01 4.13",
      "start": [
        43.81,
        16.97
      ],
      "end": [
        0.01,
        4.13
      ]
    },
    {
      "index": 7,
      "path": "M 57.7 25.83 c 0.84 0.84 1.29 1.64 1.32 2.6 c 0.73 3.28 1.74 8.32 2.54 12.8 c 0.22 1.23 0.42 2.41 0.6 3.5",
      "start": [
        57.7,
        25.83
      ],
      "end": [
        0.6,
        3.5
      ]
    },
    {
      "index": 8,
      "path": "M 59.92 26.71 C 69.04 25.23 76.15 24.04 83.65 23.06 c 1.88 -0.24 3.17 0.8 2.75 2.49 c -1.14 4.65 -1.64 6.36 -3.63 14.11",
      "start": [
        59.92,
        26.71
      ],
      "end": [
        -3.63,
        14.11
      ]
    },
    {
      "index": 9,
      "path": "M 63.05 42.94 c 3.58 -0.4 11.18 -1.27 17.25 -1.9 c 1.41 -0.15 2.73 -0.29 3.87 -0.44",
      "start": [
        63.05,
        42.94
      ],
      "end": [
        3.87,
        -0.44
      ]
    },
    {
      "index": 10,
      "path": "M 27.98 58.69 c 2.14 0.53 4.39 0.49 6.53 0.23 c 6.39 -0.77 23 -2.54 32.35 -3.11 c 1.9 -0.11 3.79 -0.27 5.61 0.39",
      "start": [
        27.98,
        58.69
      ],
      "end": [
        5.61,
        0.39
      ]
    },
    {
      "index": 11,
      "path": "M 49.41 59.86 c 0.81 0.81 1.13 1.94 1.13 3.39 C 50.54 67.89 50.53 77.06 50.53 81.65",
      "start": [
        49.41,
        59.86
      ],
      "end": [
        50.53,
        81.65
      ]
    },
    {
      "index": 12,
      "path": "M 29.82 70.87 c 2.02 0.43 4.05 0.28 6.07 0.08 c 8.69 -0.85 21.56 -2.26 30.4 -2.73 c 2.31 -0.12 4.46 -0.22 6.41 0.13",
      "start": [
        29.82,
        70.87
      ],
      "end": [
        6.41,
        0.13
      ]
    },
    {
      "index": 13,
      "path": "M 20.41 84.58 c 3.44 0.51 6.94 0.36 10.09 0.03 c 15.35 -1.59 29.28 -3.07 45.65 -3.72 c 2.73 -0.11 6.99 0.2 8.94 0.74",
      "start": [
        20.41,
        84.58
      ],
      "end": [
        8.94,
        0.74
      ]
    }
  ]
}